kryten/CONFIG.md
kryten/__init__.py
kryten/__main__.py
kryten/application_state.py
kryten/audit_logger.py
kryten/command_subscriber.py
kryten/config.example.json
kryten/config.py
kryten/connection_watchdog.py
kryten/correlation.py
kryten/cytube_connector.py
kryten/cytube_event_sender.py
kryten/errors.py
kryten/event_publisher.py
kryten/health_monitor.py
kryten/lifecycle_events.py
kryten/logging_config.py
kryten/nats_client.py
kryten/raw_event.py
kryten/robot_command_handler.py
kryten/service_registry.py
kryten/shutdown_handler.py
kryten/socket_io.py
kryten/state_manager.py
kryten/state_query_handler.py
kryten/state_updater.py
kryten/stats_tracker.py
kryten/subject_builder.py
kryten_robot-0.8.1.dist-info/METADATA
kryten_robot-0.8.1.dist-info/WHEEL
kryten_robot-0.8.1.dist-info/entry_points.txt
kryten_robot-0.8.1.dist-info/licenses/LICENSE
kryten_robot-0.8.1.dist-info/RECORD
