Metadata-Version: 2.4
Name: kryten-robot
Version: 0.8.1
Summary: CyTube to NATS bridge connector - publishes CyTube events to NATS message bus
Author: Kryten Robot Team
License: MIT
License-File: LICENSE
Keywords: bridge,connector,cytube,microservices,nats,socketio
Classifier: Development Status :: 4 - Beta
Classifier: Intended Audience :: Developers
Classifier: License :: OSI Approved :: MIT License
Classifier: Programming Language :: Python :: 3
Classifier: Programming Language :: Python :: 3.10
Classifier: Programming Language :: Python :: 3.11
Classifier: Programming Language :: Python :: 3.12
Classifier: Topic :: Communications :: Chat
Classifier: Topic :: Software Development :: Libraries :: Python Modules
Classifier: Topic :: System :: Distributed Computing
Requires-Python: <4.0.0,>=3.10
Requires-Dist: aiohttp>=3.9.0
Requires-Dist: nats-py<3.0.0,>=2.9.0
Requires-Dist: psutil<6.0.0,>=5.9.0
Requires-Dist: pydantic-settings<3.0.0,>=2.0.0
Requires-Dist: pydantic<3.0.0,>=2.0.0
Requires-Dist: python-socketio>=5.11.0
Requires-Dist: websockets>=12.0
